shouldpy/__init__.py
shouldpy/py.typed
shouldpy/should.py
shouldpy-1.0.1.dist-info/licenses/LICENSE
shouldpy-1.0.1.dist-info/METADATA
shouldpy-1.0.1.dist-info/WHEEL
shouldpy-1.0.1.dist-info/top_level.txt
shouldpy-1.0.1.dist-info/RECORD
