Metadata-Version: 2.4
Name: shouldpy
Version: 1.0.1
Summary: AI-driven test assertion decorator for natural language testing
Author-email: zx <your-email@example.com>
License: MIT
Project-URL: Homepage, https://github.com/zhixiangxue/should-ai
Project-URL: Repository, https://github.com/zhixiangxue/should-ai
Project-URL: Documentation, https://github.com/zhixiangxue/should-ai#readme
Project-URL: Bug Tracker, https://github.com/zhixiangxue/should-ai/issues
Project-URL: Changelog, https://github.com/zhixiangxue/should-ai/blob/main/CHANGELOG.md
Keywords: testing,ai,assertion,decorator,llm,natural-language
Classifier: Development Status :: 4 - Beta
Classifier: Intended Audience :: Developers
Classifier: License :: OSI Approved :: MIT License
Classifier: Operating System :: OS Independent
Classifier: Programming Language :: Python :: 3
Classifier: Programming Language :: Python :: 3.8
Classifier: Programming Language :: Python :: 3.9
Classifier: Programming Language :: Python :: 3.10
Classifier: Programming Language :: Python :: 3.11
Classifier: Programming Language :: Python :: 3.12
Classifier: Topic :: Software Development :: Testing
Classifier: Topic :: Software Development :: Quality Assurance
Requires-Python: >=3.8
License-File: LICENSE
Requires-Dist: langchain-openai>=0.1.0
Provides-Extra: dev
Requires-Dist: pytest>=6.0; extra == "dev"
Requires-Dist: pytest-asyncio>=0.21.0; extra == "dev"
Requires-Dist: black>=22.0; extra == "dev"
Requires-Dist: isort>=5.0; extra == "dev"
Requires-Dist: mypy>=1.0; extra == "dev"
Provides-Extra: anthropic
Requires-Dist: langchain-anthropic>=0.1.0; extra == "anthropic"
Provides-Extra: gemini
Requires-Dist: langchain-google-genai>=0.1.0; extra == "gemini"
Dynamic: license-file
